{
  "id": 24169604,
  "magazineId": 1778990,
  "title": "캉이, 너는 인마, 변명이 너무 많아",
  "subTitle": "철학자 박구용",
  "summary": "라캉의 주이상스를 만난 김어준의 난동 테라피",
  "image": "https://img.podbbang.com/pbi/0/656/214/000214656/214656.jpg",
  "isFree": false,
  "issue": {
    "id": 2157,
    "title": "2021년 9월호",
    "isPaid": false,
    "isPublished": true,
    "canSubscribe": true,
    "canPay": false,
    "canPayConfirm": null,
    "permissions": {
      "play": false,
      "feedback": false,
      "support": false,
      "commentView": true,
      "commentAction": false
    }
  },
  "likeCount": 489,
  "media": {
    "duration": "01:15:53",
    "url": "https://cdn.podbbang.com/guide/paidcontent.mp3"
  },
  "description": "<div class=\"image\"><img src=\"https://dimg.podbbang.com/ch/0/1778990/playlist_2157/1632921209_073600.jpeg?w=750&h=1000\"><p class=\"description\">자크 라캉 Jacques Lacan 1902-1981 ⓒBymar<br><br>1932. 편집증 연구로 의학박사 학위<br>1936. 국제정신분석학회에서 ‘거울단계’ 발표 중 퇴장<br>1953~ '프로이트로의 복귀'를 위한 세미나<br>1963. 국제정신분석학회 축출<br>1964. 파리 프로이트 학교 건립<br>1966. 『에크리』출간<br>1968. 68운동 지지<br><br>상징계와 욕망에 관해 주창한 1950~60년대를 라캉의 전기, 실재계와 주이상스를 설파한 70년대를 후기로 분류한다. <br><br><br></p></div><div class=\"image\"><img src=\"https://dimg.podbbang.com/ch/0/1778990/playlist_2157/1632921209_732100.jpeg?w=750&h=999\"><p class=\"description\">지그문트 프로이트 Sigmund Freud 1856-1939<br><br>오스트리아의 정신과 의사, 정신분석학의 창시자. 라캉은 프로이트로의 귀환을 역설하며 철학, 언어학을 차용하여 프로이트 이론을 재해석하고 쇄신했다. <br><br>라캉은 수없이 많은 세미나와 강연을 열었는데 자신의 청중들에게 “당신들은 라캉주의자들인가요, 저는 프로이트주의자입니다.”라고 말한 일화는 유명하다. <br><br><br></p></div><div class=\"image\"><img src=\"https://dimg.podbbang.com/ch/0/1778990/playlist_2157/1632921209_335800.jpeg?w=750&h=999\"><p class=\"description\">『에크리』 1966년 초판 <br><br>글보다 말로써 철학적 작업을 하고자 했던 라캉이 남긴 유일한 저작. 30여편의 글을 엮은 책으로 지성계는 물론 대중의 호응도 폭발적이었지만 난해하기로 유명하다. 아래는 『에크리』에 등장하는 주요 개념들.<br><br>:시니피앙 (signifiant)<br>소쉬르에 의하면 언어의 최소 단위를 기호로 볼 때 기호는 소리와 개념으로 조합된다. 소리를 기표(시니피앙), 개념을 기의(시니피에)라 한다. 라캉은 여기에서 언어의 최소 단위는 기호가 아니라 시니피앙-기표, 즉 소리-발음이라고 했다.  <br> <br>:상상계 (imaginary)<br>자아 의식에 수용되는 이미지들의 세계. 어머니의 욕망과 동일화를 이루는 단계<br><br>:상징계 (symbolic)<br>언어가 만들어낸 구조화된 세계. 아버지의 등장<br><br>:실재계 (real)<br>상징화를 벗어나는 모든 영역. 상징계의 바깥이면서 동시에 구조적 원인<br><br><br></p></div><div class=\"image\"><img src=\"https://dimg.podbbang.com/ch/0/1778990/playlist_2157/1632921209_767700.jpeg?w=750&h=996\"><p class=\"description\">고등학교 시절의 김어준 편집장<br><br><br><br><br></p></div><div class=\"image\"><img src=\"https://dimg.podbbang.com/ch/0/1778990/playlist_2157/1632921210_015000.jpeg?w=750&h=999\"><p class=\"description\"></p></div><div class=\"playlist\"><h3 class=\"sub-title\">게스트</h3><h1 class=\"title\">박구용</h1><h2 class=\"description\">전남대 철학과 교수</h2></div>"
}