{
  "id": 24768782,
  "magazineId": 1778990,
  "title": "<비텐베르크 제단화> 루터의 성서주의를 담다",
  "subTitle": "미술사학자 노성두",
  "summary": "원탁, 후광, 세례, 화이트 와인, 고해성사, 핏자국",
  "image": "https://img.podbbang.com/pbi/0/328/391/000391328/391328.jpg",
  "isFree": false,
  "issue": {
    "id": 3556,
    "title": "2023년 8월호",
    "isPaid": false,
    "isPublished": true,
    "canSubscribe": true,
    "canPay": false,
    "canPayConfirm": null,
    "permissions": {
      "play": false,
      "feedback": false,
      "support": false,
      "commentView": true,
      "commentAction": false
    }
  },
  "likeCount": 906,
  "media": {
    "duration": "01:04:51",
    "url": "https://cdn.podbbang.com/guide/paidcontent.mp3"
  },
  "description": "<div class=\"image\"><img src=\"https://dimg.podbbang.com/ch/0/1778990/playlist_3556/1693388102_496600.jpeg?w=750&h=1187\"><p class=\"description\">마틴 루터Martin Luther, 1483~1546<br><br>로마 가톨릭 교회의 부패에 반기를 든 독일의 종교개혁가. 가톨릭 교회의 교리와 폐쇄성에 의문을 제기하고 성경을 통한 하나님과의 직접적인 접촉과 하나님의 구원을 설파하였으며, 라틴어로 되어 있던 성경을 독일어로 번역하여 대중화에 기여했다.<br><br><br><br><br></p></div><div class=\"image\"><img src=\"https://dimg.podbbang.com/ch/0/1778990/playlist_3556/1693388102_638800.jpeg?w=750&h=1035\"><p class=\"description\">알카소바스 조약<br><br>1479년 9월 4일 스페인과 포르투갈 사이에 체결된 조약으로, 카스티야 왕위 계승전을 종결시키기 위해 체결되었다. 조약의 주요 내용은 이사벨 1세의 왕위 인정하며 북위 26도 이남의 모든 영토는 포르투갈이 소유하게 된다는 것이다.<br><br><br><br><br></p></div><div class=\"image\"><img src=\"https://dimg.podbbang.com/ch/0/1778990/playlist_3556/1693388172_165300.jpeg?w=750&h=1029\"><p class=\"description\">토르데시아스 협정<br><br>1494년 스페인과 포르투갈 사이에 체결된 협정으로, 유럽에서 인도로 향하는 해양을 양국이 분할한 조약이다. 이 조약은 스페인의 지원을 받은 콜럼버스가 신대륙을 발견하고 귀국한 즉히 로마 교황 알렉산드르 6세에게 새로 발견한 지역, 즉 아메리카와 그 서쪽 모두가 스페인의 영토임을 인정해 달라고 요청한 데서 비롯되었다. 교황은 카보베르데 제도에서 서쪽으로 480km 떨어진 지점에 경계선을 긋고 서쪽 지역은 스페인이, 동쪽 지역은 포르투갈이 차지하게 했다.<br><br><br><br><br></p></div><div class=\"image\"><img src=\"https://dimg.podbbang.com/ch/0/1778990/playlist_3556/1693388102_310000.jpeg?w=750&h=780\"><p class=\"description\">마틴 루터의 데드 마스크<br>ⓒPaul T. McCain.<br><br><br><br><br></p></div><div class=\"image\"><img src=\"https://dimg.podbbang.com/ch/0/1778990/playlist_3556/1693388102_358300.jpeg?w=750&h=772\"><p class=\"description\">마틴 루터와 카나리나 폰 보라의 결혼<br>ⓒBildarchiv-Foto-Marburg / Rolf-W.Nehrdich<br><br><br><br><br></p></div><div class=\"image\"><img src=\"https://dimg.podbbang.com/ch/0/1778990/playlist_3556/1693388102_030700.jpeg?w=750&h=1125\"><p class=\"description\">크라나흐, 비텐베르크 제단화<br>ⓒW. Bulach<br><br>1547~1548년, 패널에 유채, 103.5×233cm<br>비텐베르크 시교회<br><br>왼쪽 상단 - 세례<br>중앙 상단 - 최후의 만찬(성찬례)<br>오른쪽 상단 - 고해성사<br>중앙 하단 - 루터의 설교<br><br><br><br><br></p></div><div class=\"image\"><img src=\"https://dimg.podbbang.com/ch/0/1778990/playlist_3556/1693388102_716100.jpeg?w=750&h=786\"><p class=\"description\">크라나흐, 비텐베르크 제단화 중 <최후의 만찬><br><br><br><br><br></p></div><div class=\"image\"><img src=\"https://dimg.podbbang.com/ch/0/1778990/playlist_3556/1693388102_053500.jpeg?w=750&h=1050\"><p class=\"description\">1490년경 그려진 것으로 추정되는 <최후의 만찬><br>ⓒRosenwald Collection<br><br><br><br><br></p></div><div class=\"image\"><img src=\"https://dimg.podbbang.com/ch/0/1778990/playlist_3556/1693388102_700100.jpeg?w=750&h=571\"><p class=\"description\">크라나흐, <최후의 만찬> 속 예수<br><br><br><br><br></p></div><div class=\"image\"><img src=\"https://dimg.podbbang.com/ch/0/1778990/playlist_3556/1693388102_554200.jpeg?w=704&h=578\"><p class=\"description\">크라나흐, <최후의 만찬> 속 루터와 크라나흐 아들<br><br>크라나흐의 아들(오른쪽)이 루터(왼쪽)에게 술잔을 건네주고 있다.<br><br><br><br><br></p></div><div class=\"image\"><img src=\"https://dimg.podbbang.com/ch/0/1778990/playlist_3556/1693388172_224100.jpeg?w=750&h=751\"><p class=\"description\">안드레아스 카를슈타트Andreas Karlstadt, 1486~1541<br><br>종교 개혁 시대에 활동한 급진 종교개혁가. 작센의 선제후 프레데릭 3세가 루터를 바르트부르크에 은신시킨 후 카를슈타트는 비텐베르크에서 최초의 성상 파괴 운동을 시작했다.<br><br><br><br><br></p></div><div class=\"image\"><img src=\"https://dimg.podbbang.com/ch/0/1778990/playlist_3556/1693388102_836100.jpeg?w=750&h=558\"><p class=\"description\"></p></div><div class=\"image\"><img src=\"https://dimg.podbbang.com/ch/0/1778990/playlist_3556/1693388103_741600.jpeg?w=750&h=545\"><p class=\"description\">크라나흐, <최후의 만찬> 속 화이트 와인<br><br><br><br><br></p></div><div class=\"image\"><img src=\"https://dimg.podbbang.com/ch/0/1778990/playlist_3556/1693388103_326200.jpeg?w=750&h=1796\"><p class=\"description\">크라나흐, 비텐베르크 제단화 중 <고해성사><br><br><br><br><br></p></div><div class=\"image\"><img src=\"https://dimg.podbbang.com/ch/0/1778990/playlist_3556/1693388103_870900.jpeg?w=750&h=1143\"><p class=\"description\">요하네스 부겐하겐Johannes Bugenhagen, 1485~1558<br><br>16세기 포메라니아 공국과 덴마크에 개신교 종교 개혁을 도입한 독일의 신학자이자 루터교 사제. 비텐베르크 성 마리아 교회의 목사였다.<br><br><br><br><br></p></div><div class=\"image\"><img src=\"https://dimg.podbbang.com/ch/0/1778990/playlist_3556/1693388103_265100.jpeg?w=750&h=987\"><p class=\"description\">루벤스, <성 베드로><br>1610~1612년, 패널에 유채, 107×82cm<br><br>베드로가 예수로부터 열쇠를 부여받았다는 이유로 베드로의 후계인 가톨릭 교황에게만 열쇠의 권능이 주어진다고 여겨졌다.<br><br><br><br><br></p></div><div class=\"image\"><img src=\"https://dimg.podbbang.com/ch/0/1778990/playlist_3556/1693388103_008400.jpeg?w=750&h=1747\"><p class=\"description\">크라나흐, 비텐베르크 제단화 중 <세례><br><br><br><br><br></p></div><div class=\"image\"><img src=\"https://dimg.podbbang.com/ch/0/1778990/playlist_3556/1693388103_432800.jpeg?w=750&h=471\"><p class=\"description\">아이슬레벤 성 페트리-파울리 교회 내부의 세례반<br>ⓒDguendel<br><br><br><br><br></p></div><div class=\"image\"><img src=\"https://dimg.podbbang.com/ch/0/1778990/playlist_3556/1693388103_897300.jpeg?w=750&h=1033\"><p class=\"description\">필리프 멜란히톤Philipp Melanchthon, 1497~1560<br><br>독일의 종교개혁가, 인문주의자이자 비텐베르크 대학의 그리스어 교수. 루터의 종교 개혁 운동의 동료로서 종교개혁운동을 통한 복음주의의 확립을 위해 투쟁했다. <br><br><br><br><br></p></div><div class=\"image\"><img src=\"https://dimg.podbbang.com/ch/0/1778990/playlist_3556/1693388103_935000.jpeg?w=750&h=286\"><p class=\"description\">크라나흐, 비텐베르크 제단화 중 <루터의 설교><br><br><br><br><br></p></div><div class=\"image\"><img src=\"https://dimg.podbbang.com/ch/0/1778990/playlist_3556/1693388103_404700.jpeg?w=750&h=1017\"><p class=\"description\">크라나흐, <루터의 설교> 중앙에 위치한 십자가 예수<br><br>십자가가 바닥에 박혀 있지 않고 얹혀져 있는 것을 확인할 수 있다.<br><br><br><br><br></p></div><div class=\"image\"><img src=\"https://dimg.podbbang.com/ch/0/1778990/playlist_3556/1693388103_304100.jpeg?w=750&h=329\"><p class=\"description\">크라나흐 비텐베르크 제단화 상부 명문<br><br>“아무도 이미 놓인 기초 외에 다른 기초를 놓을 수 없기 때문입니다. 그 기초는 예수 그리스도이십니다. (1 코린토, 3:11)”<br><br><br><br><br></p></div><div class=\"image\"><img src=\"https://dimg.podbbang.com/ch/0/1778990/playlist_3556/1693388103_957200.jpeg?w=750&h=1019\"><p class=\"description\">크라나흐, <루터의 설교> 왼쪽에 위치한 신자들<br><br>루터의 설교를 열심히 경청하고 있다.<br><br><br><br><br></p></div><div class=\"image\"><img src=\"https://dimg.podbbang.com/ch/0/1778990/playlist_3556/1693388103_889500.jpeg?w=750&h=560\"><p class=\"description\">게오르그 펜츠, <두 개의 설교><br>1529년경, 목판화, 29.5×39.2cm<br><br><br><br><br></p></div><div class=\"image\"><img src=\"https://dimg.podbbang.com/ch/0/1778990/playlist_3556/1693388103_929700.jpeg?w=750&h=1129\"><p class=\"description\">토르가우의 설교단<br>ⓒAndreas Praefcke<br><br>크라나흐가 <루터의 설교>를 그리면서 참고했을 것으로 여겨진다.<br><br><br><br><br><br><br></p></div><div class=\"image\"><img src=\"https://dimg.podbbang.com/ch/0/1778990/playlist_3556/1693388103_268300.jpeg?w=750&h=1000\"><p class=\"description\"></p></div><div class=\"playlist\"><h3 class=\"sub-title\">게스트</h3><h1 class=\"title\">노성두</h1><h2 class=\"description\">미술사학자<br><br>사진. LESS</h2></div>"
}