{
  "id": 24939927,
  "magazineId": 1778990,
  "title": "뇌과학의 하드 프라블럼, 컨셔스니스",
  "subTitle": "전자공학박사 박문호",
  "summary": "에델먼, 크릭, 토노니 의식 탐구 최전선",
  "image": "https://img.podbbang.com/pbi/0/657/452/000452657/452657.jpg",
  "isFree": false,
  "issue": {
    "id": 3948,
    "title": "2024년 5월호",
    "isPaid": false,
    "isPublished": true,
    "canSubscribe": true,
    "canPay": false,
    "canPayConfirm": null,
    "permissions": {
      "play": false,
      "feedback": false,
      "support": false,
      "commentView": true,
      "commentAction": false
    }
  },
  "likeCount": 921,
  "media": {
    "duration": "00:47:19",
    "url": "https://cdn.podbbang.com/guide/paidcontent.mp3"
  },
  "description": "<div class=\"image\"><img src=\"https://dimg.podbbang.com/ch/0/1778990/playlist_3948/1717127873_444100.jpeg?w=683&h=1024\"><p class=\"description\">제럴드 모리스 에덜먼 Gerald Maurice Edelman, 1929~2014<br />ⓒAnders L&aring;ngberg<br /><br />미국의 생물학자로, 항체 분자의 구조 발견에 관한 연구로 노벨상을 수상했다.<br />에델먼은 면역 체계의 구성 요소가 진화하는 방식과 뇌의 구성 요소가 진화하는 방식의 유사성에 주목하며 의식에 대해 생물학적 진화 이론과 형태학적 시냅스 연결 이론을 주장했다.<br /><br /><br /><br /></p></div><div class=\"image\"><img src=\"https://dimg.podbbang.com/ch/0/1778990/playlist_3948/1717128136_284700.jpeg?w=750&h=617\"><p class=\"description\"><div>데이비드 존 차머스 David John Chalmers, 1966~<br />ⓒDannyGolcman<br /><br />호주의 철학자로, 현대과학이 의식을 설명할 수 없다는 것을 논증했다.<br />물질에 불과한 뇌가 감각을 주관적으로 느끼는 이유를 설명하지 못하는 것에 대해 어려운 문제(hard problem)라는 개념을 사용하며 의식 자체를 자연의 기본적인 구성 요소로 상정해야 한다고 주장했다.<br /><br /><br /><br /><br /><br /></div></p></div><div class=\"image\"><img src=\"https://dimg.podbbang.com/ch/0/1778990/playlist_3948/1717128137_655100.jpeg?w=750&h=558\"><p class=\"description\"><div>프란시스 크릭 Francis Crick, 1916~2004<br /><br />영국의 생물학자로, DNA의 이중 나선 구조에 관한 연구로 노벨상을 수상했다.<br />많은 신경생물학자들이 의식을 금기시하는 것에 충격을 받고 의식에 대한 이론적 연구에 집중했으며, 의식이 단기 기억 과정을 포함하기 때문에 이해하기 어렵다고 주장했다.<br /><br /><br /><br /><br /><br /></div></p></div><div class=\"image\"><img src=\"https://dimg.podbbang.com/ch/0/1778990/playlist_3948/1717128137_289700.jpeg?w=750&h=1000\"><p class=\"description\"><div>크리스토프 코흐 Christof Koch, 1956~<br /><br />독일계 미국인 신경과학자로 프랜시스 크릭과 함께 의식을 연구했다. <br />신경생물학적 방법으로 뇌의 구조와 의식 사이의 관계를 접근하며 전장(Claustrum)을 통해 의식의 작동 과정을 해결할 수 있다고 주장했다.<br /><br /><br /><br /><br /><br /></div></p></div><div class=\"image\"><img src=\"https://dimg.podbbang.com/ch/0/1778990/playlist_3948/1717128137_719000.jpeg?w=750&h=596\"><p class=\"description\">박문호 박사의 에델먼 도표<br /><br /><br /><br /><br /><br /></p></div><div class=\"image\"><img src=\"https://dimg.podbbang.com/ch/0/1778990/playlist_3948/1717128137_226800.jpeg?w=750&h=750\"><p class=\"description\"><div>줄리오 토노니 Giulio Tonini, 1960~<br />ⓒCenter for Sleep and Consciousness<br /><br />이탈리아의 신경과학자이자 정신과 의사로, 의식에 대해 수학적으로 접근하며 의식을 측정하는 방법과 뇌와의 연관성에 관한 이론인 '통합정보이론(Integrated Information Theory)'을 개발했다.<br /><br /><br /><br /><br /><br /></div></p></div><div class=\"image\"><img src=\"https://dimg.podbbang.com/ch/0/1778990/playlist_3948/1717128137_628100.jpeg?w=750&h=1127\"><p class=\"description\">『내가 된다는 것』 아닐 세스(지은이)ㅣ장혜인(옮긴이)ㅣ흐름출판ㅣ2022<br /><br /><br /><br /><br /><br /></p></div><div class=\"image\"><img src=\"https://dimg.podbbang.com/ch/0/1778990/playlist_3948/1717129070_640200.jpeg?w=750&h=500\"><p class=\"description\"><div>칼 프리스턴 Karl Priston, 1959~<br /><br />영국의 신경과학자로, 물리학에서 영감을 받아 프리 에너지 이론을 개발했다.<br />뇌가 내부 모델을 기반으로 예측하고 감각 입력을 통해 놀라움과 불확실성을 줄임으로써 예측 정확도를 높이기 위해 내부 세계와 외부 세계를 정렬하려는 목적을 갖는다고 주장했다.<br /><br /><br /><br /><br /><br /></div></p></div><div class=\"image\"><img src=\"https://dimg.podbbang.com/ch/0/1778990/playlist_3948/1717128137_358900.jpeg?w=750&h=1000\"><p class=\"description\"></p></div><div class=\"playlist\"><h3 class=\"sub-title\">게스트</h3><h1 class=\"title\">박문호</h1><h2 class=\"description\">전자공학박사<br /><br />사진. LESS</h2></div>"
}